{
  "c3eabc4bac": {
    "name": "valtanhm",
    "datetime": "<t:1667718000:F>",
    "count": 1,
    "party": {
      "member1": "mijumaru",
      "member2": " ",
      "member3": " ",
      "member4": " ",
      "member5": " ",
      "member6": " ",
      "member7": " ",
      "member8": " "
    },
    "class": {
      "member1": "Paladin",
      "member2": " ",
      "member3": " ",
      "member4": " ",
      "member5": " ",
      "member6": " ",
      "member7": " ",
      "member8": " "
    }
  },
  "f0fe042be4": {
    "name": "valtanhm",
    "datetime": "<t:1667718000:F>",
    "count": 0,
    "party": {
      "member1": " ",
      "member2": " ",
      "member3": " ",
      "member4": " ",
      "member5": " ",
      "member6": " ",
      "member7": " ",
      "member8": " "
    },
    "class": {
      "member1": " ",
      "member2": " ",
      "member3": " ",
      "member4": " ",
      "member5": " ",
      "member6": " ",
      "member7": " ",
      "member8": " "
    }
  },
  "e23f501427": {
    "name": "valtanhm",
    "datetime": "<t:1667718000:F>",
    "count": 0,
    "party": {
      "member1": " ",
      "member2": " ",
      "member3": " ",
      "member4": " ",
      "member5": " ",
      "member6": " ",
      "member7": " ",
      "member8": " "
    },
    "class": {
      "member1": " ",
      "member2": " ",
      "member3": " ",
      "member4": " ",
      "member5": " ",
      "member6": " ",
      "member7": " ",
      "member8": " "
    }
  }
}